bookmuse/__init__.py
bookmuse/main.py
bookmuse/prompts.py
bookmuse-2025.12.22083751.dist-info/METADATA
bookmuse-2025.12.22083751.dist-info/WHEEL
bookmuse-2025.12.22083751.dist-info/top_level.txt
bookmuse-2025.12.22083751.dist-info/RECORD
