Metadata-Version: 2.4
Name: bookmuse
Version: 2025.12.22083751
Summary: bookmuse generates personalized reading lists based on user preferences and reading history.
Author-email: bookmuse <hi@eugene.plus>
License: MIT
Project-URL: Homepage, https://github.com/chigwell/bookmuse
Requires-Python: >=3.9
Requires-Dist: langchain-llm7>=0.0.0
Requires-Dist: llmatch-messages>=0.0.0
Requires-Dist: langchain-core>=0.3.0
